django_opstasks/__init__.py
django_opstasks/admin.py
django_opstasks/apps.py
django_opstasks/base.py
django_opstasks/dashboard.py
django_opstasks/database.py
django_opstasks/managers.py
django_opstasks/models.py
django_opstasks/schedulers.py
django_opstasks/tasks.py
django_opstasks/urls.py
django_opstasks/views.py
django_opstasks/backends/__init__.py
django_opstasks/backends/cache.py
django_opstasks/backends/database.py
django_opstasks/common/__init__.py
django_opstasks/common/datetime.py
django_opstasks/common/notifications.py
django_opstasks/common/requests.py
django_opstasks/common/response.py
django_opstasks/common/sqlalchemy.py
django_opstasks/migrations/0001_initial.py
django_opstasks/migrations/0002_auto_20200901_2215.py
django_opstasks/migrations/0003_auto_20200901_2231.py
django_opstasks/migrations/0004_taskdashboard.py
django_opstasks/migrations/__init__.py
django_opstasks-0.2.10.dist-info/METADATA
django_opstasks-0.2.10.dist-info/WHEEL
django_opstasks-0.2.10.dist-info/entry_points.txt
django_opstasks-0.2.10.dist-info/top_level.txt
django_opstasks-0.2.10.dist-info/RECORD
