Metadata-Version: 2.1
Name: django-opstasks
Version: 0.2.10
Summary: opstasks
Home-page: UNKNOWN
Author: lunuan
Author-email: admin@lunuan.com.cn
License: BSD
Keywords: opstasks
Platform: any
Classifier: Development Status :: 1 - Planning
Classifier: License :: OSI Approved :: BSD License
Classifier: Programming Language :: Python
Classifier: Programming Language :: Python :: 3.7
Classifier: Programming Language :: Python :: 3.8
Classifier: Programming Language :: Python :: Implementation :: CPython
Classifier: Programming Language :: Python :: Implementation :: PyPy
Classifier: Framework :: Django
Classifier: Framework :: Django :: 3.0
Classifier: Operating System :: OS Independent
Classifier: Topic :: Communications
Classifier: Topic :: System :: Distributed Computing
Classifier: Topic :: Software Development :: Libraries :: Python Modules
Requires-Dist: celery (<5.0,>=4.4)
